MCPacker/MCPacker.py
MCPacker/__about__.py
MCPacker/__init__.py
MCPacker/__main__.py
mcpacker-1.0.3.dist-info/METADATA
mcpacker-1.0.3.dist-info/WHEEL
mcpacker-1.0.3.dist-info/entry_points.txt
mcpacker-1.0.3.dist-info/licenses/LICENSE.TXT
mcpacker-1.0.3.dist-info/RECORD
