Metadata-Version: 2.1
Name: MCPacker
Version: 1.0.3
Summary: A tool to easily pack Minecraft addons.
Project-URL: Homepage, https://codeberg.org/DidierMalenfant/MCPacker
Author-email: Didier Malenfant <coding@malenfant.net>
License-Expression: MIT
License-File: LICENSE.TXT
Keywords: addon,minecraft
Classifier: Development Status :: 4 - Beta
Classifier: Programming Language :: Python
Classifier: Programming Language :: Python :: Implementation :: CPython
Classifier: Programming Language :: Python :: Implementation :: PyPy
Requires-Python: >=3.8
Requires-Dist: semver
